pysasl/__about__.py
pysasl/__init__.py
pysasl/exception.py
pysasl/hashing.py
pysasl/identity.py
pysasl/prep.py
pysasl/py.typed
pysasl/creds/__init__.py
pysasl/creds/client.py
pysasl/creds/external.py
pysasl/creds/plain.py
pysasl/creds/server.py
pysasl/mechanism/__init__.py
pysasl/mechanism/crammd5.py
pysasl/mechanism/external.py
pysasl/mechanism/login.py
pysasl/mechanism/oauth.py
pysasl/mechanism/plain.py
pysasl-1.2.0.dist-info/METADATA
pysasl-1.2.0.dist-info/WHEEL
pysasl-1.2.0.dist-info/entry_points.txt
pysasl-1.2.0.dist-info/licenses/LICENSE.md
pysasl-1.2.0.dist-info/RECORD
