Metadata-Version: 2.1
Name: pysasl
Version: 1.2.0
Summary: Pure Python SASL client and server library.
Project-URL: Homepage, https://github.com/icgood/pysasl/
Project-URL: API Documentation, https://icgood.github.io/pysasl/
Author-email: Ian Good <ian@icgood.net>
License: ## The MIT License (MIT)
License-File: LICENSE.md
Classifier: Development Status :: 3 - Alpha
Classifier: Intended Audience :: Developers
Classifier: Intended Audience :: Information Technology
Classifier: License :: OSI Approved :: MIT License
Classifier: Programming Language :: Python
Classifier: Programming Language :: Python :: 3.7
Classifier: Programming Language :: Python :: 3.8
Classifier: Programming Language :: Python :: 3.9
Classifier: Programming Language :: Python :: 3.10
Classifier: Programming Language :: Python :: 3.11
Requires-Python: ~=3.7
Requires-Dist: importlib-metadata; python_version < '3.10'
Requires-Dist: typing-extensions
